macrobot/__init__.py
macrobot/bgt.py
macrobot/bipolaris.py
macrobot/cli.py
macrobot/helpers.py
macrobot/log.txt
macrobot/mb_pipeline.py
macrobot/orga.py
macrobot/prediction.py
macrobot/puccinia.py
macrobot/puccinia_ipk.py
macrobot/report.html
macrobot/requirements.txt
macrobot/segmentation.py
macrobot/tests/__init__.py
macrobot/tests/gb2_exp40_leaf.csv
macrobot/tests/image_backlight.npy
macrobot/tests/image_blue.npy
macrobot/tests/image_green.npy
macrobot/tests/image_red.npy
macrobot/tests/image_rgb.npy
macrobot/tests/image_tresholded.npy
macrobot/tests/image_uvs.npy
macrobot/tests/lanes_roi_backlight.npy
macrobot/tests/lanes_roi_binary.npy
macrobot/tests/lanes_roi_minrgb.npy
macrobot/tests/lanes_roi_rgb.npy
macrobot/tests/max_rgb_data.npy
macrobot/tests/min_rgb_data.npy
macrobot/tests/predicted_lanes.npy
macrobot/tests/test_helpers.py
macrobot/tests/test_mildew.py
macrobot/tests/whitebalance_data.npy
macrobot-0.9.0.dist-info/entry_points.txt
macrobot-0.9.0.dist-info/LICENSE.txt
macrobot-0.9.0.dist-info/WHEEL
macrobot-0.9.0.dist-info/METADATA
macrobot-0.9.0.dist-info/RECORD
